requests_custom/__init__.py
requests_custom/requests_custom.py
requests_custom-0.0.6.dist-info/LICENSE
requests_custom-0.0.6.dist-info/METADATA
requests_custom-0.0.6.dist-info/WHEEL
requests_custom-0.0.6.dist-info/top_level.txt
requests_custom-0.0.6.dist-info/RECORD
