Metadata-Version: 2.1
Name: requests-custom
Version: 0.0.6
Summary: Python's requests with custom configuration
Author: Carlos A Molina
Project-URL: Documentation, https://requests-custom.readthedocs.io
Project-URL: Source, https://github.com/carlosamolina/requests_custom
Classifier: Programming Language :: Python :: 3.6
Classifier: Programming Language :: Python :: 3.7
Classifier: Programming Language :: Python :: 3.8
Classifier: License :: OSI Approved :: MIT License
Classifier: Operating System :: OS Independent
Requires-Python: >=3.6
License-File: LICENSE
Requires-Dist: requests (>=2.23.0)
Requires-Dist: requests-toolbelt (>=0.9.1)
